AUTHORS
LICENSE
MANIFEST.in
README.rst
setup.py
django_phased.egg-info/PKG-INFO
django_phased.egg-info/SOURCES.txt
django_phased.egg-info/dependency_links.txt
django_phased.egg-info/top_level.txt
phased/__init__.py
phased/middleware.py
phased/models.py
phased/test_cases.py
phased/test_settings.py
phased/utils.py
phased/templatetags/__init__.py
phased/templatetags/phased_tags.py