Metadata-Version: 1.1
Name: django-phased
Version: 0.6.1
Summary: Simple two-phase template rendering application useful for caching of authenticated requests.
Home-page: http://github.com/codysoyland/django-phased
Author: Cody Soyland
Author-email: codysoyland@gmail.com
License: BSD
Platform: UNKNOWN
Classifier: Development Status :: 4 - Beta
Classifier: Framework :: Django
Classifier: Intended Audience :: Developers
Classifier: License :: OSI Approved :: BSD License
Classifier: Operating System :: OS Independent
Classifier: Programming Language :: Python
Classifier: Topic :: Internet :: WWW/HTTP
